flask_url_map_serializer.py
flask_url_map_serializer-0.0.1.dist-info/METADATA
flask_url_map_serializer-0.0.1.dist-info/RECORD
flask_url_map_serializer-0.0.1.dist-info/WHEEL
flask_url_map_serializer-0.0.1.dist-info/entry_points.txt
flask_url_map_serializer-0.0.1.dist-info/top_level.txt
