Metadata-Version: 2.1
Name: flask-url-map-serializer
Version: 0.0.1
Summary: Dumps the URL map of a flask app to a JSON file
Home-page: https://github.com/indico/babel-plugin-flask-urls
Author: Indico Team
Author-email: indico-team@cern.ch
License: MIT
